{
  "fetched": "2026-04-29T11:26:03Z",
  "version": 5,
  "count": 13,
  "total_found": 43,
  "tier_breakdown": {
    "direct_ag": 0,
    "trade_energy": 31,
    "macro_weather": 12
  },
  "categories": {
    "Trade & Policy": [
      {
        "platform": "Polymarket",
        "ticker": "567687",
        "title": "Russia x Ukraine ceasefire by end of 2026?",
        "yes": 26,
        "no": 74,
        "volume_24h": 14502613.985482976,
        "close_time": "2026-12-31T00:00:00Z",
        "time_left": "Closes in ~8mo",
        "url": "https://polymarket.com/event/russia-x-ukraine-ceasefire-before-2027",
        "slug": "russia-x-ukraine-ceasefire-before-2027",
        "relevance": 70,
        "tier": 2,
        "category": "Trade & Policy",
        "why_it_matters": "Market prices 74% odds the conflict continues through 2026. Black Sea grain corridors remain a wild card for global wheat and corn supply; Ukraine has historically accounted for roughly 10% of world wheat exports when corridors are open."
      },
      {
        "platform": "Polymarket",
        "ticker": "1171663",
        "title": "Russia x Ukraine ceasefire by June 30, 2026?",
        "yes": 8,
        "no": 92,
        "volume_24h": 6681560.832979033,
        "close_time": "2026-06-30T00:00:00Z",
        "time_left": "Closes in ~2mo",
        "url": "https://polymarket.com/event/russia-x-ukraine-ceasefire-by-june-30-2026",
        "slug": "russia-x-ukraine-ceasefire-by-june-30-2026",
        "relevance": 70,
        "tier": 2,
        "category": "Trade & Policy",
        "why_it_matters": "Market prices 92% odds the conflict continues through 2026. Black Sea grain corridors remain a wild card for global wheat and corn supply; Ukraine has historically accounted for roughly 10% of world wheat exports when corridors are open."
      },
      {
        "platform": "Polymarket",
        "ticker": "956449",
        "title": "Ukraine signs peace deal with Russia by June 30?",
        "yes": 6,
        "no": 94,
        "volume_24h": 99886.33485200001,
        "close_time": "2026-06-30T00:00:00Z",
        "time_left": "Closes in ~2mo",
        "url": "https://polymarket.com/event/ukraine-signs-peace-deal-with-russia-by-june-30",
        "slug": "ukraine-signs-peace-deal-with-russia-by-june-30",
        "relevance": 70,
        "tier": 2,
        "category": "Trade & Policy",
        "why_it_matters": "Reflects conditions that can affect agricultural commodity prices, input costs, or farm policy."
      }
    ],
    "Energy & Inputs": [
      {
        "platform": "Polymarket",
        "ticker": "1712297",
        "title": "Will WTI Crude Oil (WTI) hit (HIGH) $120 in April?",
        "yes": 2,
        "no": 98,
        "volume_24h": 6010332.158255979,
        "close_time": "2026-04-30T00:00:00Z",
        "time_left": "Closes today",
        "url": "https://polymarket.com/event/will-wti-crude-oil-wti-hit-high-120-in-april",
        "slug": "will-wti-crude-oil-wti-hit-high-120-in-april",
        "relevance": 70,
        "tier": 2,
        "category": "Energy & Inputs",
        "why_it_matters": "Tail-risk bet (2% odds) on crude reach $120. Closes today. Would lift farm diesel and pass through to nitrogen fertilizer cost within a few months."
      },
      {
        "platform": "Polymarket",
        "ticker": "1494703",
        "title": "Will Crude Oil (CL) hit (HIGH) $200 by end of June?",
        "yes": 5,
        "no": 95,
        "volume_24h": 2781926.3143030023,
        "close_time": "2026-06-30T18:30:00Z",
        "time_left": "Closes in ~2mo",
        "url": "https://polymarket.com/event/will-crude-oil-cl-hit-high-200-by-end-of-june-677",
        "slug": "will-crude-oil-cl-hit-high-200-by-end-of-june-677",
        "relevance": 70,
        "tier": 2,
        "category": "Energy & Inputs",
        "why_it_matters": "Tail-risk bet (5% odds) on crude reach $200. Closes in ~2mo. Would lift farm diesel and pass through to nitrogen fertilizer cost within a few months."
      },
      {
        "platform": "Polymarket",
        "ticker": "1929111",
        "title": "Will WTI Crude Oil (WTI) hit (LOW) $75 in April?",
        "yes": 1,
        "no": 99,
        "volume_24h": 1289776.6281679987,
        "close_time": "2026-04-30T00:00:00Z",
        "time_left": "Closes today",
        "url": "https://polymarket.com/event/will-wti-crude-oil-wti-hit-low-75-in-april-729-763-439-856-448-294-921-116-755",
        "slug": "will-wti-crude-oil-wti-hit-low-75-in-april-729-763-439-856-448-294-921-116-755",
        "relevance": 70,
        "tier": 2,
        "category": "Energy & Inputs",
        "why_it_matters": "Tail-risk bet (1% odds) on crude drop below $75. Closes today. A move this low would ease diesel and nitrogen input cost pressure heading into side-dress and summer ops."
      },
      {
        "platform": "Polymarket",
        "ticker": "1980675",
        "title": "Will WTI Crude Oil (WTI) hit (HIGH) $105 in April?",
        "yes": 62,
        "no": 38,
        "volume_24h": 841079.0287650012,
        "close_time": "2026-04-30T00:00:00Z",
        "time_left": "Closes today",
        "url": "https://polymarket.com/event/will-wti-crude-oil-wti-hit-high-105-in-april-yyy",
        "slug": "will-wti-crude-oil-wti-hit-high-105-in-april-yyy",
        "relevance": 70,
        "tier": 2,
        "category": "Energy & Inputs",
        "why_it_matters": "Market pricing 62% odds crude will reach $105. Closes today. Would lift farm diesel and pass through to nitrogen fertilizer cost within a few months."
      },
      {
        "platform": "Polymarket",
        "ticker": "1652677",
        "title": "Will Crude Oil (CL) hit (HIGH) $120 by end of June?",
        "yes": 49,
        "no": 51,
        "volume_24h": 451239.15635599993,
        "close_time": "2026-06-30T18:30:00Z",
        "time_left": "Closes in ~2mo",
        "url": "https://polymarket.com/event/will-crude-oil-cl-hit-high-120-by-end-of-june-949-198-741-748",
        "slug": "will-crude-oil-cl-hit-high-120-by-end-of-june-949-198-741-748",
        "relevance": 70,
        "tier": 2,
        "category": "Energy & Inputs",
        "why_it_matters": "Near coin-flip odds (49% YES) crude reach $120. Closes in ~2mo. Would lift farm diesel and pass through to nitrogen fertilizer cost within a few months."
      },
      {
        "platform": "Polymarket",
        "ticker": "1652697",
        "title": "Will Crude Oil (CL) hit (LOW) $70 by end of June?",
        "yes": 26,
        "no": 74,
        "volume_24h": 206749.8352559994,
        "close_time": "2026-06-30T18:30:00Z",
        "time_left": "Closes in ~2mo",
        "url": "https://polymarket.com/event/will-crude-oil-cl-hit-low-70-by-end-of-june-776-556-989-392-677",
        "slug": "will-crude-oil-cl-hit-low-70-by-end-of-june-776-556-989-392-677",
        "relevance": 70,
        "tier": 2,
        "category": "Energy & Inputs",
        "why_it_matters": "Lower-probability outcome (26%) that crude drop below $70. Closes in ~2mo. A move this low would ease diesel and nitrogen input cost pressure heading into side-dress and summer ops."
      }
    ],
    "Economy & Markets": [
      {
        "platform": "Polymarket",
        "ticker": "616902",
        "title": "Will no Fed rate cuts happen in 2026?",
        "yes": 49,
        "no": 51,
        "volume_24h": 3680672.9031780143,
        "close_time": "2026-12-31T00:00:00Z",
        "time_left": "Closes in ~8mo",
        "url": "https://polymarket.com/event/will-no-fed-rate-cuts-happen-in-2026",
        "slug": "will-no-fed-rate-cuts-happen-in-2026",
        "relevance": 40,
        "tier": 3,
        "category": "Economy & Markets",
        "why_it_matters": "49% odds of a rate cut. Lower rates reduce operating loan and land interest carrying cost -- historically supportive of commodity prices via weaker dollar."
      },
      {
        "platform": "Polymarket",
        "ticker": "906972",
        "title": "Will the Fed decrease interest rates by 50+ bps after the June 2026 meeting?",
        "yes": 1,
        "no": 99,
        "volume_24h": 3019563.0744560286,
        "close_time": "2026-06-17T00:00:00Z",
        "time_left": "Closes in ~1mo",
        "url": "https://polymarket.com/event/will-the-fed-decrease-interest-rates-by-50-bps-after-the-june-2026-meeting",
        "slug": "will-the-fed-decrease-interest-rates-by-50-bps-after-the-june-2026-meeting",
        "relevance": 40,
        "tier": 3,
        "category": "Economy & Markets",
        "why_it_matters": "Fed policy moves ripple through the dollar and farm lending -- 1% YES on this outcome."
      },
      {
        "platform": "Polymarket",
        "ticker": "616908",
        "title": "Will 6 Fed rate cuts happen in 2026?",
        "yes": 1,
        "no": 99,
        "volume_24h": 2240539.396329992,
        "close_time": "2026-12-31T00:00:00Z",
        "time_left": "Closes in ~8mo",
        "url": "https://polymarket.com/event/will-6-fed-rate-cuts-happen-in-2026",
        "slug": "will-6-fed-rate-cuts-happen-in-2026",
        "relevance": 40,
        "tier": 3,
        "category": "Economy & Markets",
        "why_it_matters": "1% odds of a rate cut. Lower rates reduce operating loan and land interest carrying cost -- historically supportive of commodity prices via weaker dollar."
      },
      {
        "platform": "Polymarket",
        "ticker": "906974",
        "title": "Will there be no change in Fed interest rates after the June 2026 meeting?",
        "yes": 94,
        "no": 6,
        "volume_24h": 2135137.3585070106,
        "close_time": "2026-06-17T00:00:00Z",
        "time_left": "Closes in ~1mo",
        "url": "https://polymarket.com/event/will-there-be-no-change-in-fed-interest-rates-after-the-june-2026-meeting",
        "slug": "will-there-be-no-change-in-fed-interest-rates-after-the-june-2026-meeting",
        "relevance": 40,
        "tier": 3,
        "category": "Economy & Markets",
        "why_it_matters": "Fed policy moves ripple through the dollar and farm lending -- 94% YES on this outcome."
      }
    ]
  },
  "markets": [
    {
      "platform": "Polymarket",
      "ticker": "567687",
      "title": "Russia x Ukraine ceasefire by end of 2026?",
      "yes": 26,
      "no": 74,
      "volume_24h": 14502613.985482976,
      "close_time": "2026-12-31T00:00:00Z",
      "time_left": "Closes in ~8mo",
      "url": "https://polymarket.com/event/russia-x-ukraine-ceasefire-before-2027",
      "slug": "russia-x-ukraine-ceasefire-before-2027",
      "relevance": 70,
      "tier": 2,
      "category": "Trade & Policy",
      "why_it_matters": "Market prices 74% odds the conflict continues through 2026. Black Sea grain corridors remain a wild card for global wheat and corn supply; Ukraine has historically accounted for roughly 10% of world wheat exports when corridors are open."
    },
    {
      "platform": "Polymarket",
      "ticker": "1171663",
      "title": "Russia x Ukraine ceasefire by June 30, 2026?",
      "yes": 8,
      "no": 92,
      "volume_24h": 6681560.832979033,
      "close_time": "2026-06-30T00:00:00Z",
      "time_left": "Closes in ~2mo",
      "url": "https://polymarket.com/event/russia-x-ukraine-ceasefire-by-june-30-2026",
      "slug": "russia-x-ukraine-ceasefire-by-june-30-2026",
      "relevance": 70,
      "tier": 2,
      "category": "Trade & Policy",
      "why_it_matters": "Market prices 92% odds the conflict continues through 2026. Black Sea grain corridors remain a wild card for global wheat and corn supply; Ukraine has historically accounted for roughly 10% of world wheat exports when corridors are open."
    },
    {
      "platform": "Polymarket",
      "ticker": "1712297",
      "title": "Will WTI Crude Oil (WTI) hit (HIGH) $120 in April?",
      "yes": 2,
      "no": 98,
      "volume_24h": 6010332.158255979,
      "close_time": "2026-04-30T00:00:00Z",
      "time_left": "Closes today",
      "url": "https://polymarket.com/event/will-wti-crude-oil-wti-hit-high-120-in-april",
      "slug": "will-wti-crude-oil-wti-hit-high-120-in-april",
      "relevance": 70,
      "tier": 2,
      "category": "Energy & Inputs",
      "why_it_matters": "Tail-risk bet (2% odds) on crude reach $120. Closes today. Would lift farm diesel and pass through to nitrogen fertilizer cost within a few months."
    },
    {
      "platform": "Polymarket",
      "ticker": "1494703",
      "title": "Will Crude Oil (CL) hit (HIGH) $200 by end of June?",
      "yes": 5,
      "no": 95,
      "volume_24h": 2781926.3143030023,
      "close_time": "2026-06-30T18:30:00Z",
      "time_left": "Closes in ~2mo",
      "url": "https://polymarket.com/event/will-crude-oil-cl-hit-high-200-by-end-of-june-677",
      "slug": "will-crude-oil-cl-hit-high-200-by-end-of-june-677",
      "relevance": 70,
      "tier": 2,
      "category": "Energy & Inputs",
      "why_it_matters": "Tail-risk bet (5% odds) on crude reach $200. Closes in ~2mo. Would lift farm diesel and pass through to nitrogen fertilizer cost within a few months."
    },
    {
      "platform": "Polymarket",
      "ticker": "1929111",
      "title": "Will WTI Crude Oil (WTI) hit (LOW) $75 in April?",
      "yes": 1,
      "no": 99,
      "volume_24h": 1289776.6281679987,
      "close_time": "2026-04-30T00:00:00Z",
      "time_left": "Closes today",
      "url": "https://polymarket.com/event/will-wti-crude-oil-wti-hit-low-75-in-april-729-763-439-856-448-294-921-116-755",
      "slug": "will-wti-crude-oil-wti-hit-low-75-in-april-729-763-439-856-448-294-921-116-755",
      "relevance": 70,
      "tier": 2,
      "category": "Energy & Inputs",
      "why_it_matters": "Tail-risk bet (1% odds) on crude drop below $75. Closes today. A move this low would ease diesel and nitrogen input cost pressure heading into side-dress and summer ops."
    },
    {
      "platform": "Polymarket",
      "ticker": "1980675",
      "title": "Will WTI Crude Oil (WTI) hit (HIGH) $105 in April?",
      "yes": 62,
      "no": 38,
      "volume_24h": 841079.0287650012,
      "close_time": "2026-04-30T00:00:00Z",
      "time_left": "Closes today",
      "url": "https://polymarket.com/event/will-wti-crude-oil-wti-hit-high-105-in-april-yyy",
      "slug": "will-wti-crude-oil-wti-hit-high-105-in-april-yyy",
      "relevance": 70,
      "tier": 2,
      "category": "Energy & Inputs",
      "why_it_matters": "Market pricing 62% odds crude will reach $105. Closes today. Would lift farm diesel and pass through to nitrogen fertilizer cost within a few months."
    },
    {
      "platform": "Polymarket",
      "ticker": "1652677",
      "title": "Will Crude Oil (CL) hit (HIGH) $120 by end of June?",
      "yes": 49,
      "no": 51,
      "volume_24h": 451239.15635599993,
      "close_time": "2026-06-30T18:30:00Z",
      "time_left": "Closes in ~2mo",
      "url": "https://polymarket.com/event/will-crude-oil-cl-hit-high-120-by-end-of-june-949-198-741-748",
      "slug": "will-crude-oil-cl-hit-high-120-by-end-of-june-949-198-741-748",
      "relevance": 70,
      "tier": 2,
      "category": "Energy & Inputs",
      "why_it_matters": "Near coin-flip odds (49% YES) crude reach $120. Closes in ~2mo. Would lift farm diesel and pass through to nitrogen fertilizer cost within a few months."
    },
    {
      "platform": "Polymarket",
      "ticker": "1652697",
      "title": "Will Crude Oil (CL) hit (LOW) $70 by end of June?",
      "yes": 26,
      "no": 74,
      "volume_24h": 206749.8352559994,
      "close_time": "2026-06-30T18:30:00Z",
      "time_left": "Closes in ~2mo",
      "url": "https://polymarket.com/event/will-crude-oil-cl-hit-low-70-by-end-of-june-776-556-989-392-677",
      "slug": "will-crude-oil-cl-hit-low-70-by-end-of-june-776-556-989-392-677",
      "relevance": 70,
      "tier": 2,
      "category": "Energy & Inputs",
      "why_it_matters": "Lower-probability outcome (26%) that crude drop below $70. Closes in ~2mo. A move this low would ease diesel and nitrogen input cost pressure heading into side-dress and summer ops."
    },
    {
      "platform": "Polymarket",
      "ticker": "956449",
      "title": "Ukraine signs peace deal with Russia by June 30?",
      "yes": 6,
      "no": 94,
      "volume_24h": 99886.33485200001,
      "close_time": "2026-06-30T00:00:00Z",
      "time_left": "Closes in ~2mo",
      "url": "https://polymarket.com/event/ukraine-signs-peace-deal-with-russia-by-june-30",
      "slug": "ukraine-signs-peace-deal-with-russia-by-june-30",
      "relevance": 70,
      "tier": 2,
      "category": "Trade & Policy",
      "why_it_matters": "Reflects conditions that can affect agricultural commodity prices, input costs, or farm policy."
    },
    {
      "platform": "Polymarket",
      "ticker": "616902",
      "title": "Will no Fed rate cuts happen in 2026?",
      "yes": 49,
      "no": 51,
      "volume_24h": 3680672.9031780143,
      "close_time": "2026-12-31T00:00:00Z",
      "time_left": "Closes in ~8mo",
      "url": "https://polymarket.com/event/will-no-fed-rate-cuts-happen-in-2026",
      "slug": "will-no-fed-rate-cuts-happen-in-2026",
      "relevance": 40,
      "tier": 3,
      "category": "Economy & Markets",
      "why_it_matters": "49% odds of a rate cut. Lower rates reduce operating loan and land interest carrying cost -- historically supportive of commodity prices via weaker dollar."
    },
    {
      "platform": "Polymarket",
      "ticker": "906972",
      "title": "Will the Fed decrease interest rates by 50+ bps after the June 2026 meeting?",
      "yes": 1,
      "no": 99,
      "volume_24h": 3019563.0744560286,
      "close_time": "2026-06-17T00:00:00Z",
      "time_left": "Closes in ~1mo",
      "url": "https://polymarket.com/event/will-the-fed-decrease-interest-rates-by-50-bps-after-the-june-2026-meeting",
      "slug": "will-the-fed-decrease-interest-rates-by-50-bps-after-the-june-2026-meeting",
      "relevance": 40,
      "tier": 3,
      "category": "Economy & Markets",
      "why_it_matters": "Fed policy moves ripple through the dollar and farm lending -- 1% YES on this outcome."
    },
    {
      "platform": "Polymarket",
      "ticker": "616908",
      "title": "Will 6 Fed rate cuts happen in 2026?",
      "yes": 1,
      "no": 99,
      "volume_24h": 2240539.396329992,
      "close_time": "2026-12-31T00:00:00Z",
      "time_left": "Closes in ~8mo",
      "url": "https://polymarket.com/event/will-6-fed-rate-cuts-happen-in-2026",
      "slug": "will-6-fed-rate-cuts-happen-in-2026",
      "relevance": 40,
      "tier": 3,
      "category": "Economy & Markets",
      "why_it_matters": "1% odds of a rate cut. Lower rates reduce operating loan and land interest carrying cost -- historically supportive of commodity prices via weaker dollar."
    },
    {
      "platform": "Polymarket",
      "ticker": "906974",
      "title": "Will there be no change in Fed interest rates after the June 2026 meeting?",
      "yes": 94,
      "no": 6,
      "volume_24h": 2135137.3585070106,
      "close_time": "2026-06-17T00:00:00Z",
      "time_left": "Closes in ~1mo",
      "url": "https://polymarket.com/event/will-there-be-no-change-in-fed-interest-rates-after-the-june-2026-meeting",
      "slug": "will-there-be-no-change-in-fed-interest-rates-after-the-june-2026-meeting",
      "relevance": 40,
      "tier": 3,
      "category": "Economy & Markets",
      "why_it_matters": "Fed policy moves ripple through the dollar and farm lending -- 94% YES on this outcome."
    }
  ]
}