{
  "fetched": "2026-04-28T19:05:26Z",
  "ok": 40,
  "failed": 1,
  "quotes": {
    "corn": {
      "ticker": "ZC=F",
      "close": 475.5,
      "open": 469.25,
      "netChange": 6.25,
      "pctChange": 1.3319,
      "wk52_hi": 477.25,
      "wk52_lo": 368.75
    },
    "corn-dec": {
      "ticker": "ZCZ26.CBT",
      "close": 495.75,
      "open": 490.0,
      "netChange": 5.75,
      "pctChange": 1.1735,
      "wk52_hi": 498.5,
      "wk52_lo": 440.75
    },
    "beans": {
      "ticker": "ZS=F",
      "close": 1190.25,
      "open": 1187.25,
      "netChange": 3.0,
      "pctChange": 0.2527,
      "wk52_hi": 1223.25,
      "wk52_lo": 960.75
    },
    "beans-nov": {
      "ticker": "ZSX26.CBT",
      "close": 1167.75,
      "open": 1162.75,
      "netChange": 5.0,
      "pctChange": 0.43,
      "wk52_hi": 1174.25,
      "wk52_lo": 1023.25
    },
    "wheat": {
      "ticker": "ZW=F",
      "close": 658.25,
      "open": 631.75,
      "netChange": 26.5,
      "pctChange": 4.1947,
      "wk52_hi": 635.0,
      "wk52_lo": 492.25
    },
    "oats": {
      "ticker": "ZO=F",
      "close": 348.0,
      "open": 345.75,
      "netChange": 2.25,
      "pctChange": 0.6508,
      "wk52_hi": 403.5,
      "wk52_lo": 272.0
    },
    "corn-jul26": {
      "ticker": "ZCN26.CBT",
      "close": 475.5,
      "open": 469.25,
      "netChange": 6.25,
      "pctChange": 1.3319,
      "wk52_hi": 487.5,
      "wk52_lo": 428.5
    },
    "corn-sep26": {
      "ticker": "ZCU26.CBT",
      "close": 480.5,
      "open": 474.5,
      "netChange": 6.0,
      "pctChange": 1.2645,
      "wk52_hi": 488.0,
      "wk52_lo": 431.25
    },
    "corn-mar27": {
      "ticker": "ZCH27.CBT",
      "close": 508.75,
      "open": 503.25,
      "netChange": 5.5,
      "pctChange": 1.0929,
      "wk52_hi": 506.75,
      "wk52_lo": 454.25
    },
    "corn-may27": {
      "ticker": "ZCK27.CBT",
      "close": 515.75,
      "open": 510.5,
      "netChange": 5.25,
      "pctChange": 1.0284,
      "wk52_hi": 513.0,
      "wk52_lo": 461.25
    },
    "corn-jul27": {
      "ticker": "ZCN27.CBT",
      "close": 518.75,
      "open": 514.0,
      "netChange": 4.75,
      "pctChange": 0.9241,
      "wk52_hi": 515.75,
      "wk52_lo": 463.5
    },
    "corn-dec27": {
      "ticker": "ZCZ27.CBT",
      "close": 500.25,
      "open": 497.75,
      "netChange": 2.5,
      "pctChange": 0.5023,
      "wk52_hi": 498.0,
      "wk52_lo": 451.75
    },
    "beans-jul26": {
      "ticker": "ZSN26.CBT",
      "close": 1190.25,
      "open": 1187.25,
      "netChange": 3.0,
      "pctChange": 0.2527,
      "wk52_hi": 1250.75,
      "wk52_lo": 1043.0
    },
    "beans-aug26": {
      "ticker": "ZSQ26.CBT",
      "close": 1184.75,
      "open": 1180.0,
      "netChange": 4.75,
      "pctChange": 0.4025,
      "wk52_hi": 1231.0,
      "wk52_lo": 1043.75
    },
    "beans-sep26": {
      "ticker": "ZSU26.CBT",
      "close": 1162.75,
      "open": 1158.5,
      "netChange": 4.25,
      "pctChange": 0.3669,
      "wk52_hi": 1183.5,
      "wk52_lo": 1031.0
    },
    "beans-jan27": {
      "ticker": "ZSF27.CBT",
      "close": 1179.5,
      "open": 1174.25,
      "netChange": 5.25,
      "pctChange": 0.4471,
      "wk52_hi": 1186.5,
      "wk52_lo": 1039.75
    },
    "beans-mar27": {
      "ticker": "ZSH27.CBT",
      "close": 1176.25,
      "open": 1171.5,
      "netChange": 4.75,
      "pctChange": 0.4055,
      "wk52_hi": 1184.25,
      "wk52_lo": 1040.75
    },
    "beans-jul27": {
      "ticker": "ZSN27.CBT",
      "close": 1183.75,
      "open": 1180.0,
      "netChange": 3.75,
      "pctChange": 0.3178,
      "wk52_hi": 1193.0,
      "wk52_lo": 1053.5
    },
    "beans-nov27": {
      "ticker": "ZSX27.CBT",
      "close": 1134.5,
      "open": 1132.5,
      "netChange": 2.0,
      "pctChange": 0.1766,
      "wk52_hi": 1144.5,
      "wk52_lo": 1039.25
    },
    "wheat-jul26": {
      "ticker": "ZWN26.CBT",
      "close": 658.25,
      "open": 631.75,
      "netChange": 26.5,
      "pctChange": 4.1947,
      "wk52_hi": 650.25,
      "wk52_lo": 525.75
    },
    "wheat-sep26": {
      "ticker": "ZWU26.CBT",
      "close": 671.75,
      "open": 644.25,
      "netChange": 27.5,
      "pctChange": 4.2685,
      "wk52_hi": 661.0,
      "wk52_lo": 539.75
    },
    "wheat-dec26": {
      "ticker": "ZWZ26.CBT",
      "close": 689.75,
      "open": 663.25,
      "netChange": 26.5,
      "pctChange": 3.9955,
      "wk52_hi": 676.25,
      "wk52_lo": 557.25
    },
    "wheat-mar27": {
      "ticker": "ZWH27.CBT",
      "close": 704.25,
      "open": 679.0,
      "netChange": 25.25,
      "pctChange": 3.7187,
      "wk52_hi": 684.75,
      "wk52_lo": 572.5
    },
    "wheat-jul27": {
      "ticker": "ZWN27.CBT",
      "close": 699.75,
      "open": 679.75,
      "netChange": 20.0,
      "pctChange": 2.9423,
      "wk52_hi": 681.0,
      "wk52_lo": 583.5
    },
    "wheat-dec27": {
      "ticker": "ZWZ27.CBT",
      "close": 711.5,
      "open": 690.0,
      "netChange": 21.5,
      "pctChange": 3.1159,
      "wk52_hi": 694.75,
      "wk52_lo": 607.25
    },
    "cattle": {
      "ticker": "LE=F",
      "close": 253.45,
      "open": 248.97501,
      "netChange": 4.47499,
      "pctChange": 1.7974,
      "wk52_hi": 253.6,
      "wk52_lo": 204.55
    },
    "feeders": {
      "ticker": "GF=F",
      "close": 373.07501,
      "open": 368.32501,
      "netChange": 4.75,
      "pctChange": 1.2896,
      "wk52_hi": 381.025,
      "wk52_lo": 291.65
    },
    "hogs": {
      "ticker": "HE=F",
      "close": 102.0,
      "open": 102.175,
      "netChange": -0.175,
      "pctChange": -0.1713,
      "wk52_hi": 113.7,
      "wk52_lo": 77.35
    },
    "milk": {
      "ticker": "DC=F",
      "close": 17.7,
      "open": 17.88,
      "netChange": -0.18,
      "pctChange": -1.0067,
      "wk52_hi": 18.89,
      "wk52_lo": 14.53
    },
    "meal": {
      "ticker": "ZM=F",
      "close": 328.79999,
      "open": 327.89999,
      "netChange": 0.9,
      "pctChange": 0.2745,
      "wk52_hi": 339.6,
      "wk52_lo": 258.6
    },
    "soyoil": {
      "ticker": "ZL=F",
      "close": 72.43,
      "open": 71.71,
      "netChange": 0.72,
      "pctChange": 1.004,
      "wk52_hi": 73.32,
      "wk52_lo": 45.74
    },
    "crude": {
      "ticker": "CL=F",
      "close": 100.16,
      "open": 97.57,
      "netChange": 2.59,
      "pctChange": 2.6545,
      "wk52_hi": 119.48,
      "wk52_lo": 54.98
    },
    "natgas": {
      "ticker": "NG=F",
      "close": 2.683,
      "open": 2.72,
      "netChange": -0.037,
      "pctChange": -1.3603,
      "wk52_hi": 7.827,
      "wk52_lo": 2.495
    },
    "gold": {
      "ticker": "GC=F",
      "close": 4608.7998,
      "open": 4685.6001,
      "netChange": -76.8003,
      "pctChange": -1.6391,
      "wk52_hi": 5586.2002,
      "wk52_lo": 3125.0
    },
    "silver": {
      "ticker": "SI=F",
      "close": 73.78,
      "open": 74.635,
      "netChange": -0.855,
      "pctChange": -1.1456,
      "wk52_hi": 121.3,
      "wk52_lo": 31.685
    },
    "dollar": {
      "ticker": "DX=F",
      "close": 100.0,
      "open": 99.873,
      "netChange": 0.127,
      "pctChange": 0.1272
    },
    "treasury10": {
      "ticker": "^TNX",
      "close": 4.351,
      "open": 4.336,
      "netChange": 0.015,
      "pctChange": 0.3459,
      "wk52_hi": 4.629,
      "wk52_lo": 3.947
    },
    "sp500": {
      "ticker": "^GSPC",
      "close": 7140.5498,
      "open": 7174.00977,
      "netChange": -33.45997,
      "pctChange": -0.4664,
      "wk52_hi": 7178.7402,
      "wk52_lo": 5433.2402
    },
    "bitcoin": {
      "ticker": "BTC-USD",
      "close": 76145.21094,
      "open": 77364.42188,
      "netChange": -1219.21094,
      "pctChange": -1.5759,
      "wk52_hi": 126198.0703,
      "wk52_lo": 60074.2031
    },
    "ripple": {
      "ticker": "XRP-USD",
      "close": 1.3804,
      "open": 1.4006,
      "netChange": -0.0202,
      "pctChange": -1.4422,
      "wk52_hi": 3.6502,
      "wk52_lo": 1.1335
    },
    "kaspa": {
      "ticker": "KAS-USD",
      "close": 0.03268,
      "open": 0.03336,
      "netChange": -0.00068,
      "pctChange": -2.0384,
      "wk52_hi": 0.1308,
      "wk52_lo": 0.0139
    }
  }
}